Workbook

Sheet Dashboard
B2: DASHBOARD DE VENDAS XBOX & GAMING
B4: Visão executiva de desempenho de vendas, lucratividade e análise por categoria/canal.
B6: FATURAMENTO TOTAL | E6: UNIDADES VENDIDAS | H6: TICKET MÉDIO | K6: LUCRO TOTAL
B7: =Calculos_KPIs!B3 | E7: =Calculos_KPIs!B4 | H7: =Calculos_KPIs!B5 | K7: =Calculos_KPIs!B6

Sheet Base_de_Dados
A1: ID Venda | B1: Data | C1: Mês/Ano | D1: Produto | E1: Categoria | F1: Canal de Venda | G1: Região | H1: Qtd Vendida | I1: Preço Unitário (R$) | J1: Faturamento (R$) | K1: Custo Unitário (R$) | L1: Lucro Total (R$)
A2: XBX-2024001 | B2: 45349 | C2: 2024-02 | D2: Console Xbox Series X 1TB | E2: Console | F2: Loja Física | G2: Sul | H2: 3 | I2: 4499 | J2: =H2*I2 | K2: 3800 | L2: =J2-(H2*K2)
A3: XBX-2024002 | B3: 45406 | C3: 2024-04 | D3: Controle Sem Fio Xbox - Carbon Black | E3: Acessório | F3: Marketplace | G3: Norte | H3: 1 | I3: 499 | J3: =H3*I3 | K3: 320 | L3: =J3-(H3*K3)
A4: XBX-2024003 | B4: 45336 | C4: 2024-02 | D4: EA Sports FC 24 - Xbox Series | E4: Jogo | F4: E-commerce | G4: Sudeste | H4: 7 | I4: 350 | J4: =H4*I4 | K4: 200 | L4: =J4-(H4*K4)
A5: XBX-2024004 | B5: 45339 | C5: 2024-02 | D5: Controle Sem Fio Xbox - Robot White | E5: Acessório | F5: Marketplace | G5: Norte | H5: 2 | I5: 499 | J5: =H5*I5 | K5: 320 | L5: =J5-(H5*K5)
A6: XBX-2024005 | B6: 45305 | C6: 2024-01 | D6: Forza Horizon 5 Premium | E6: Jogo | F6: Marketplace | G6: Norte | H6: 4 | I6: 399 | J6: =H6*I6 | K6: 220 | L6: =J6-(H6*K6)
A7: XBX-2024006 | B7: 45506 | C7: 2024-08 | D7: Controle Sem Fio Xbox - Robot White | E7: Acessório | F7: Marketplace | G7: Nordeste | H7: 4 | I7: 499 | J7: =H7*I7 | K7: 320 | L7: =J7-(H7*K7)
A8: XBX-2024007 | B8: 45295 | C8: 2024-01 | D8: Cyberpunk 2077: Phantom Liberty | E8: Jogo | F8: Marketplace | G8: Centro-Oeste | H8: 3 | I8: 299 | J8: =H8*I8 | K8: 150 | L8: =J8-(H8*K8)
A9: XBX-2024008 | B9: 45466 | C9: 2024-06 | D9: Headset Sem Fio Xbox Stereo | E9: Acessório | F9: E-commerce | G9: Nordeste | H9: 2 | I9: 799 | J9: =H9*I9 | K9: 550 | L9: =J9-(H9*K9)
A10: XBX-2024009 | B10: 45344 | C10: 2024-02 | D10: Console Xbox Series S 512GB | E10: Console | F10: E-commerce | G10: Nordeste | H10: 2 | I10: 2649 | J10: =H10*I10 | K10: 2100 | L10: =J10-(H10*K10)
A11: XBX-2024010 | B11: 45468 | C11: 2024-06 | D11: EA Sports FC 24 - Xbox Series | E11: Jogo | F11: E-commerce | G11: Centro-Oeste | H11: 5 | I11: 350 | J11: =H11*I11 | K11: 200 | L11: =J11-(H11*K11)
A12: XBX-2024011 | B12: 45566 | C12: 2024-10 | D12: Console Xbox Series S 512GB | E12: Console | F12: E-commerce | G12: Norte | H12: 2 | I12: 2649 | J12: =H12*I12 | K12: 2100 | L12: =J12-(H12*K12)
A13: XBX-2024012 | B13: 45442 | C13: 2024-05 | D13: Halo Infinite Campaign | E13: Jogo | F13: Marketplace | G13: Sul | H13: 6 | I13: 249 | J13: =H13*I13 | K13: 120 | L13: =J13-(H13*K13)
... A121: XBX-2024120 | B121: 45463 | C121: 2024-06 | D121: Xbox Game Pass Ultimate 12 Meses | E121: Assinatura | F121: E-commerce | G121: Sul | H121: 9 | I121: 599 | J121: =H121*I121 | K121: 400 | L121: =J121-(H121*K121)

Sheet Calculos_KPIs
A1: RESUMO GERAL KPIs | E1: EVOLUÇÃO MENSAL
A2: Métrica | B2: Valor | E2: Mês | F2: Faturamento (R$)
A3: Faturamento Total | B3: =SUM(Base_de_Dados!J2:J121) | E3: 2024-01 | F3: =SUMIF(Base_de_Dados!C$2:C$121, E3, Base_de_Dados!J$2:J$121)
A4: Total Unidades Vendidas | B4: =SUM(Base_de_Dados!H2:H121) | E4: 2024-02 | F4: =SUMIF(Base_de_Dados!C$2:C$121, E4, Base_de_Dados!J$2:J$121)
A5: Ticket Médio Por Venda | B5: =AVERAGE(Base_de_Dados!J2:J121) | E5: 2024-03 | F5: =SUMIF(Base_de_Dados!C$2:C$121, E5, Base_de_Dados!J$2:J$121)
A6: Lucro Total | B6: =SUM(Base_de_Dados!L2:L121) | E6: 2024-04 | F6: =SUMIF(Base_de_Dados!C$2:C$121, E6, Base_de_Dados!J$2:J$121)
A7: Total de Pedidos | B7: =COUNTA(Base_de_Dados!A2:A121) | E7: 2024-05 | F7: =SUMIF(Base_de_Dados!C$2:C$121, E7, Base_de_Dados!J$2:J$121)
E8: 2024-06 | F8: =SUMIF(Base_de_Dados!C$2:C$121, E8, Base_de_Dados!J$2:J$121)
E9: 2024-07 | F9: =SUMIF(Base_de_Dados!C$2:C$121, E9, Base_de_Dados!J$2:J$121)
A10: VENDAS POR CATEGORIA | E10: 2024-08 | F10: =SUMIF(Base_de_Dados!C$2:C$121, E10, Base_de_Dados!J$2:J$121)
A11: Categoria | B11: Faturamento (R$) | C11: Qtd Vendida | E11: 2024-09 | F11: =SUMIF(Base_de_Dados!C$2:C$121, E11, Base_de_Dados!J$2:J$121)
A12: Console | B12: =SUMIF(Base_de_Dados!E$2:E$121, A12, Base_de_Dados!J$2:J$121) | C12: =SUMIF(Base_de_Dados!E$2:E$121, A12, Base_de_Dados!H$2:H$121) | E12: 2024-10 | F12: =SUMIF(Base_de_Dados!C$2:C$121, E12, Base_de_Dados!J$2:J$121)
A13: Acessório | B13: =SUMIF(Base_de_Dados!E$2:E$121, A13, Base_de_Dados!J$2:J$121) | C13: =SUMIF(Base_de_Dados!E$2:E$121, A13, Base_de_Dados!H$2:H$121)
A14: Jogo | B14: =SUMIF(Base_de_Dados!E$2:E$121, A14, Base_de_Dados!J$2:J$121) | C14: =SUMIF(Base_de_Dados!E$2:E$121, A14, Base_de_Dados!H$2:H$121)
A15: Assinatura | B15: =SUMIF(Base_de_Dados!E$2:E$121, A15, Base_de_Dados!J$2:J$121) | C15: =SUMIF(Base_de_Dados!E$2:E$121, A15, Base_de_Dados!H$2:H$121) | E15: TOP PRODUTOS
E16: Produto | F16: Faturamento (R$)
E17: Console Xbox Series X 1TB | F17: =SUMIF(Base_de_Dados!D$2:D$121, E17, Base_de_Dados!J$2:J$121)
A18: VENDAS POR CANAL | E18: Console Xbox Series S 512GB | F18: =SUMIF(Base_de_Dados!D$2:D$121, E18, Base_de_Dados!J$2:J$121)
A19: Canal | B19: Faturamento (R$) | E19: Controle Sem Fio Xbox - Carbon Black | F19: =SUMIF(Base_de_Dados!D$2:D$121, E19, Base_de_Dados!J$2:J$121)
A20: E-commerce | B20: =SUMIF(Base_de_Dados!F$2:F$121, A20, Base_de_Dados!J$2:J$121) | E20: Controle Sem Fio Xbox - Robot White | F20: =SUMIF(Base_de_Dados!D$2:D$121, E20, Base_de_Dados!J$2:J$121)
A21: Loja Física | B21: =SUMIF(Base_de_Dados!F$2:F$121, A21, Base_de_Dados!J$2:J$121) | E21: Headset Sem Fio Xbox Stereo | F21: =SUMIF(Base_de_Dados!D$2:D$121, E21, Base_de_Dados!J$2:J$121)
A22: Marketplace | B22: =SUMIF(Base_de_Dados!F$2:F$121, A22, Base_de_Dados!J$2:J$121) | E22: Xbox Game Pass Ultimate 12 Meses | F22: =SUMIF(Base_de_Dados!D$2:D$121, E22, Base_de_Dados!J$2:J$121)
E23: Xbox Game Pass Ultimate 3 Meses | F23: =SUMIF(Base_de_Dados!D$2:D$121, E23, Base_de_Dados!J$2:J$121)
E24: Starfield - Edição Standard | F24: =SUMIF(Base_de_Dados!D$2:D$121, E24, Base_de_Dados!J$2:J$121)
